{
    "SnapshotParams": {
        "Bias": {
            "@fs_enabled": false,
            "@value": 0.6499999761581421
        },
        "BrtDrive": {
            "@fs_enabled": false,
            "@value": 0.7599999904632568
        },
        "Master": {
            "@fs_enabled": false,
            "@value": 1
        },
        "Treble": {
            "@fs_enabled": false,
            "@value": 0.7300000190734863
        },
        "ChVol": {
            "@fs_enabled": false,
            "@value": 0.6000000238418579
        },
        "Ripple": {
            "@fs_enabled": false,
            "@value": 0.5
        },
        "Bass": {
            "@fs_enabled": false,
            "@value": 0.8999999761581421
        },
        "BiasX": {
            "@fs_enabled": false,
            "@value": 0.5
        },
        "Hum": {
            "@fs_enabled": false,
            "@value": 0.5
        },
        "Mid": {
            "@fs_enabled": false,
            "@value": 0.809999942779541
        },
        "NrmDrive": {
            "@fs_enabled": false,
            "@value": 0.7200000286102295
        },
        "Presence": {
            "@fs_enabled": false,
            "@value": 0.7000000476837158
        },
        "Sag": {
            "@fs_enabled": false,
            "@value": 0.5
        }
    },
    "Controller_Dict": {
        "Bias": {
            "@min": 0,
            "@max": 1,
            "@controller": 19,
            "@snapshot_disable": false
        },
        "BrtDrive": {
            "@min": 0,
            "@max": 1,
            "@controller": 19,
            "@snapshot_disable": false
        },
        "Master": {
            "@min": 0,
            "@max": 1,
            "@controller": 19,
            "@snapshot_disable": false
        },
        "Treble": {
            "@min": 0,
            "@max": 1,
            "@controller": 19,
            "@snapshot_disable": false
        },
        "ChVol": {
            "@min": 0,
            "@max": 1,
            "@controller": 19,
            "@snapshot_disable": false
        },
        "Ripple": {
            "@min": 0,
            "@max": 1,
            "@controller": 19,
            "@snapshot_disable": false
        },
        "Bass": {
            "@min": 0,
            "@max": 1,
            "@controller": 19,
            "@snapshot_disable": false
        },
        "BiasX": {
            "@min": 0,
            "@max": 1,
            "@controller": 19,
            "@snapshot_disable": false
        },
        "Hum": {
            "@min": 0,
            "@max": 1,
            "@controller": 19,
            "@snapshot_disable": false
        },
        "Mid": {
            "@min": 0,
            "@max": 1,
            "@controller": 19,
            "@snapshot_disable": false
        },
        "NrmDrive": {
            "@min": 0,
            "@max": 1,
            "@controller": 19,
            "@snapshot_disable": false
        },
        "Presence": {
            "@min": 0,
            "@max": 1,
            "@controller": 19,
            "@snapshot_disable": false
        },
        "Sag": {
            "@min": 0,
            "@max": 1,
            "@controller": 19,
            "@snapshot_disable": false
        }
    },
    "Defaults": {
        "NrmDrive": 0.7200000286102295,
        "@enabled": true,
        "@bypassvolume": 1,
        "Mid": 0.809999942779541,
        "BiasX": 0.5,
        "Bias": 0.6499999761581421,
        "@type": 3,
        "Hum": 0.5,
        "Treble": 0.7300000190734863,
        "@cab": "cab1",
        "@model": "HD2_AmpBritPlexiJump",
        "Master": 1,
        "ChVol": 0.6000000238418579,
        "@path": 0,
        "Presence": 0.7000000476837158,
        "Ripple": 0.5,
        "@position": 1,
        "@no_snapshot_bypass": false,
        "Sag": 0.5,
        "BrtDrive": 0.7599999904632568,
        "Bass": 0.8999999761581421
    }
}